bbfreeze-1.1.3.dist-info/entry_points.txt
bbfreeze-1.1.3.dist-info/top_level.txt
bbfreeze-1.1.3.dist-info/WHEEL
bbfreeze-1.1.3.dist-info/METADATA
bbfreeze-1.1.3.dist-info/pydist.json
bbfreeze-1.1.3.dist-info/RECORD
bbfreeze-1.1.3.dist-info/DESCRIPTION.rst
bbfreeze-1.1.3.data/scripts/bb-freeze
bbfreeze-1.1.3.data/scripts/bbfreeze
bbfreeze/bdist_bbfreeze.py
bbfreeze/ensure_setuptools.py
bbfreeze/load_console.py
bbfreeze/codehack.py
bbfreeze/recipes.py
bbfreeze/getdeps.py
bbfreeze/eggutil.py
bbfreeze/__init__.py
bbfreeze/winexeutil.py
bbfreeze/freezer.py
bbfreeze/__main__.py
bbfreeze/py.py
bbfreeze/modulegraph/find_modules.py
bbfreeze/modulegraph/util.py
bbfreeze/modulegraph/__init__.py
bbfreeze/modulegraph/modulegraph.py
