Metadata-Version: 2.0
Name: bbfreeze
Version: 1.1.3
Summary: create standalone executables from python scripts
Home-page: https://pypi.python.org/pypi/bbfreeze/
Author: Ralf Schmitt
Author-email: ralf@systemexit.de
License: zlib/libpng license
Platform: Linux Windows
Classifier: Development Status :: 5 - Production/Stable
Classifier: License :: OSI Approved :: zlib/libpng License
Classifier: Intended Audience :: Developers
Classifier: Programming Language :: Python
Classifier: Programming Language :: Python :: 2
Classifier: Programming Language :: Python :: 2.4
Classifier: Programming Language :: Python :: 2.5
Classifier: Programming Language :: Python :: 2.6
Classifier: Programming Language :: Python :: 2.7
Classifier: Topic :: Software Development :: Build Tools
Classifier: Topic :: System :: Software Distribution
Requires-Dist: altgraph (==0.9)
Requires-Dist: bbfreeze-loader (>=1.1.0,<1.2.0)
